larpixdaq/__init__.py
larpixdaq/aggregator.py
larpixdaq/core.py
larpixdaq/logger_producer.py
larpixdaq/offline_storage.py
larpixdaq/online_monitor.py
larpixdaq/operator.py
larpixdaq/packetformat.py
larpixdaq/producer.py
larpixdaq/routines/__init__.py
larpixdaq/routines/hello_world.py
larpixdaq/routines/quickstart.py
larpix_daq-0.2.1.dist-info/METADATA
larpix_daq-0.2.1.dist-info/WHEEL
larpix_daq-0.2.1.dist-info/top_level.txt
larpix_daq-0.2.1.dist-info/RECORD
